Metadata-Version: 1.0
Name: draft-distributions
Version: 0.1
Summary: Gaussian and Binomial distributions
Home-page: UNKNOWN
Author: Vincent
Author-email: vincentbiasa6767@gmail.com
License: UNKNOWN
Platform: UNKNOWN
